setup.py
mexbt/__init__.py
mexbt/mexbt.py
mexbt.egg-info/PKG-INFO
mexbt.egg-info/SOURCES.txt
mexbt.egg-info/dependency_links.txt
mexbt.egg-info/not-zip-safe
mexbt.egg-info/requires.txt
mexbt.egg-info/top_level.txt