Metadata-Version: 1.0
Name: mexbt
Version: 0.1
Summary: A lightweight python client for the meXBT exchange API
Home-page: http://github.com/meXBT/mexbt-python
Author: meXBT
Author-email: william@mexbt.com
License: MIT
Platform: UNKNOWN
